e3tools/__init__.py
e3tools/_pack_unpack.py
e3tools/_radius.py
e3tools/_scatter.py
e3tools/nn/__init__.py
e3tools/nn/_axis_to_mul.py
e3tools/nn/_conv.py
e3tools/nn/_extract_irreps.py
e3tools/nn/_gate.py
e3tools/nn/_interaction.py
e3tools/nn/_layer_norm.py
e3tools/nn/_linear.py
e3tools/nn/_mlp.py
e3tools/nn/_scaling.py
e3tools/nn/_tensor_product.py
e3tools/nn/_transformer.py
e3tools-0.1.3.dist-info/METADATA
e3tools-0.1.3.dist-info/WHEEL
e3tools-0.1.3.dist-info/licenses/LICENSE
e3tools-0.1.3.dist-info/RECORD
