Metadata-Version: 2.4
Name: e3tools
Version: 0.1.3
Summary: A repository of building blocks in PyTorch for E(3)/SE(3)-equivariant neural networks
Author-email: Joseph Kleinhenz <kleinhej@gene.com>, Ameya Daigavane <ameyad@mit.edu>
License-File: LICENSE
Requires-Python: >=3.10
Requires-Dist: e3nn>=0.5.5
Requires-Dist: einops>=0.8.1
Requires-Dist: jaxtyping>=0.2.38
Requires-Dist: setuptools>=78.1.0
Requires-Dist: torch>=2.5.1
Provides-Extra: dev
Requires-Dist: hatch>=1.14.0; extra == 'dev'
Requires-Dist: ipykernel>=6.30.1; extra == 'dev'
Requires-Dist: ipython>=8.34.0; extra == 'dev'
Requires-Dist: pytest>=8.3.4; extra == 'dev'
Requires-Dist: ruff; extra == 'dev'
Requires-Dist: sphinx; extra == 'dev'
